netlink/Client.py
netlink/Server.py
netlink/__init__.py
netlink/errors.py
netlink/objects.py
netlink_ipc-3.0.0.dist-info/LICENSE
netlink_ipc-3.0.0.dist-info/METADATA
netlink_ipc-3.0.0.dist-info/WHEEL
netlink_ipc-3.0.0.dist-info/top_level.txt
netlink_ipc-3.0.0.dist-info/RECORD
