Metadata-Version: 2.1
Name: netlink-ipc
Version: 3.0.0
Summary: A Basic inter-process communication (IPC) library for Client to Server communication.
Author: Suffxr
Project-URL: Homepage, https://github.com/pypa/sampleproject
Classifier: Programming Language :: Python :: 3
Classifier: License :: OSI Approved :: MIT License
Classifier: Operating System :: OS Independent
Requires-Python: >=3.8
License-File: LICENSE
